llir/__init__.py
llir/constants.py
llir/py.typed
llir/raw_input.py
llir/recorder.py
llir/send_input.py
llir/structs.py
llir-0.1.0.dist-info/licenses/LICENSE
llir-0.1.0.dist-info/METADATA
llir-0.1.0.dist-info/WHEEL
llir-0.1.0.dist-info/top_level.txt
llir-0.1.0.dist-info/RECORD
