Metadata-Version: 2.4
Name: llir
Version: 0.1.0
Summary: Low level mouse and keyboard input recorder and player.
Author-email: Yazan Sharaya <yazan.sharaya.yes@gmail.com>
License-Expression: MIT
Project-URL: Repository, https://github.com/Yazan-Sharaya/llir
Keywords: mouse,keyboard,macro
Classifier: Development Status :: 4 - Beta
Classifier: Intended Audience :: Developers
Classifier: Operating System :: Microsoft :: Windows
Classifier: Programming Language :: Python :: 3
Classifier: Programming Language :: Python :: 3.10
Classifier: Programming Language :: Python :: 3.11
Classifier: Programming Language :: Python :: 3.12
Classifier: Programming Language :: Python :: 3.13
Requires-Python: >=3.10
License-File: LICENSE
Dynamic: license-file
